Metadata-Version: 1.2
Name: espresso-server
Version: 1.0
Summary: Espresso Server for MicroPython development boards
Home-page: http://yeisoncardona.com/
Author: Yeison Cardona
Author-email: yeisoneng@gmail.com
Maintainer: Yeison Cardona
Maintainer-email: yeisoneng@gmail.com
License: BSD License
Download-URL: http://bitbucket.org/espressoide
Platform: UNKNOWN
Classifier: Environment :: Web Environment
